pytheia/__init__.py
pytheia/py.typed
pytheia/pytheia.cpython-313-x86_64-linux-gnu.so
pytheia.libs/libblas-fe34f726.so.3.8.0
pytheia.libs/libgfortran-83c28eba.so.5.0.0
pytheia.libs/liblapack-31d7d384.so.3.8.0
pytheia.libs/libquadmath-2284e583.so.0.0.0
pytheia-0.4.4.dist-info/METADATA
pytheia-0.4.4.dist-info/WHEEL
pytheia-0.4.4.dist-info/top_level.txt
pytheia-0.4.4.dist-info/RECORD
pytheia-0.4.4.dist-info/sboms/auditwheel.cdx.json
