Metadata-Version: 2.4
Name: pytheia
Version: 0.4.4
Summary: A performant Structure from Motion library for Python
Home-page: https://github.com/urbste/pyTheiaSfM.git
Author: Steffen Urban, Shengyu Yin
Author-email: urbste@googlemail.com, shengyu952014@outlook.com
License: BSD
Dynamic: author
Dynamic: author-email
Dynamic: description
Dynamic: description-content-type
Dynamic: home-page
Dynamic: license
Dynamic: summary
